{
  "audioUrl": "https://download.quranicaudio.com/qdc/mishari_al_afasy/murattal/1.mp3",
  "surah": 1,
  "wordSegments": [
    {
      "verseNum": 1,
      "wordIndex": 1,
      "start": 0.12,
      "end": 0.57
    },
    {
      "verseNum": 1,
      "wordIndex": 2,
      "start": 0.6,
      "end": 1.35
    },
    {
      "verseNum": 1,
      "wordIndex": 3,
      "start": 1.38,
      "end": 2.49
    },
    {
      "verseNum": 1,
      "wordIndex": 4,
      "start": 2.52,
      "end": 6.171
    },
    {
      "verseNum": 2,
      "wordIndex": 1,
      "start": 6.201,
      "end": 7.051
    },
    {
      "verseNum": 2,
      "wordIndex": 2,
      "start": 7.081,
      "end": 7.971
    },
    {
      "verseNum": 2,
      "wordIndex": 3,
      "start": 8.001,
      "end": 8.561
    },
    {
      "verseNum": 2,
      "wordIndex": 4,
      "start": 8.561,
      "end": 11.852
    },
    {
      "verseNum": 3,
      "wordIndex": 1,
      "start": 11.882,
      "end": 12.982
    },
    {
      "verseNum": 3,
      "wordIndex": 2,
      "start": 12.982,
      "end": 16.392
    },
    {
      "verseNum": 4,
      "wordIndex": 1,
      "start": 16.422,
      "end": 17.133
    },
    {
      "verseNum": 4,
      "wordIndex": 2,
      "start": 17.163,
      "end": 17.693
    },
    {
      "verseNum": 4,
      "wordIndex": 3,
      "start": 17.723,
      "end": 20.393
    },
    {
      "verseNum": 5,
      "wordIndex": 1,
      "start": 20.423,
      "end": 21.913
    },
    {
      "verseNum": 5,
      "wordIndex": 2,
      "start": 21.943,
      "end": 22.673
    },
    {
      "verseNum": 5,
      "wordIndex": 3,
      "start": 22.703,
      "end": 23.813
    },
    {
      "verseNum": 5,
      "wordIndex": 4,
      "start": 23.843,
      "end": 27.734
    },
    {
      "verseNum": 6,
      "wordIndex": 1,
      "start": 27.764,
      "end": 28.394
    },
    {
      "verseNum": 6,
      "wordIndex": 2,
      "start": 28.424,
      "end": 29.294
    },
    {
      "verseNum": 6,
      "wordIndex": 3,
      "start": 29.324,
      "end": 33.295
    },
    {
      "verseNum": 7,
      "wordIndex": 1,
      "start": 33.325,
      "end": 33.995
    },
    {
      "verseNum": 7,
      "wordIndex": 2,
      "start": 34.025,
      "end": 34.875
    },
    {
      "verseNum": 7,
      "wordIndex": 3,
      "start": 34.905,
      "end": 36.035
    },
    {
      "verseNum": 7,
      "wordIndex": 4,
      "start": 36.065,
      "end": 36.895
    },
    {
      "verseNum": 7,
      "wordIndex": 5,
      "start": 36.925,
      "end": 37.435
    },
    {
      "verseNum": 7,
      "wordIndex": 6,
      "start": 37.465,
      "end": 38.636
    },
    {
      "verseNum": 7,
      "wordIndex": 7,
      "start": 38.666,
      "end": 39.576
    },
    {
      "verseNum": 7,
      "wordIndex": 8,
      "start": 39.606,
      "end": 39.896
    },
    {
      "verseNum": 7,
      "wordIndex": 9,
      "start": 39.926,
      "end": 46.307
    }
  ],
  "segments": [
    {
      "verse": 1,
      "start": 0.12,
      "end": 6.171
    },
    {
      "verse": 2,
      "start": 6.201,
      "end": 11.852
    },
    {
      "verse": 3,
      "start": 11.882,
      "end": 16.392
    },
    {
      "verse": 4,
      "start": 16.422,
      "end": 20.393
    },
    {
      "verse": 5,
      "start": 20.423,
      "end": 27.734
    },
    {
      "verse": 6,
      "start": 27.764,
      "end": 33.295
    },
    {
      "verse": 7,
      "start": 33.325,
      "end": 46.307
    }
  ]
}